azuretablelogging/__init__.py
azuretablelogging/handler.py
azure_table_logging-0.2.dist-info/LICENSE
azure_table_logging-0.2.dist-info/METADATA
azure_table_logging-0.2.dist-info/WHEEL
azure_table_logging-0.2.dist-info/top_level.txt
azure_table_logging-0.2.dist-info/RECORD
