Metadata-Version: 2.1
Name: azure-table-logging
Version: 0.2
Summary: A handler class which writes formatted logging records to Azure Table Storage
Home-page: https://github.com/uezo/azure-table-storage-logging
Author: uezo
Author-email: uezo@uezo.net
Maintainer: uezo
Maintainer-email: uezo@uezo.net
License: Apache v2
Platform: UNKNOWN
Classifier: Programming Language :: Python :: 3
Requires-Dist: azure-cosmosdb-table
